fleandr_test.py
fleandr_test_package-0.2.0.dist-info/METADATA
fleandr_test_package-0.2.0.dist-info/WHEEL
fleandr_test_package-0.2.0.dist-info/top_level.txt
fleandr_test_package-0.2.0.dist-info/RECORD
