Metadata-Version: 2.4
Name: fleandr-test-package
Version: 0.2.0
Summary: Test package for PyPI cleanup utility
Author: fleandr
Author-email: fleandr@example.com
Classifier: Programming Language :: Python :: 3
Classifier: License :: OSI Approved :: MIT License
Classifier: Operating System :: OS Independent
Requires-Python: >=3.7
Dynamic: author
Dynamic: author-email
Dynamic: classifier
Dynamic: requires-python
Dynamic: summary
